imfFetcher/__init__.py
imfFetcher/consts.py
imfFetcher/main.py
imfFetcher/queries.py
imfFetcher/utils.py
imffetcher-1.0.0.dist-info/licenses/LICENSE
imffetcher-1.0.0.dist-info/METADATA
imffetcher-1.0.0.dist-info/WHEEL
imffetcher-1.0.0.dist-info/top_level.txt
imffetcher-1.0.0.dist-info/RECORD
