Metadata-Version: 2.4
Name: imfFetcher
Version: 1.0.0
Summary: Interacts with the International Monetary Fund API (SDMX 3.0) to retrieve macroeconomic data.
Author: nndjoli
License: MIT License
Project-URL: Homepage, https://github.com/nndjoli/imfFetcher
Requires-Python: >=3.8
License-File: LICENSE
Requires-Dist: httpx
Requires-Dist: pandas
Requires-Dist: nest_asyncio
Dynamic: license-file
